yypget/__init__.py
yypget/__main__.py
yypget/utils.py
yypget/executor/__init__.py
yypget/executor/sv_baidu.py
yypget/executor/tv_sohu.py
yypget/executor/wenku_baidu.py
yypget-0.0.4.dist-info/LICENSE
yypget-0.0.4.dist-info/METADATA
yypget-0.0.4.dist-info/WHEEL
yypget-0.0.4.dist-info/entry_points.txt
yypget-0.0.4.dist-info/top_level.txt
yypget-0.0.4.dist-info/RECORD
