Metadata-Version: 2.1
Name: yypget
Version: 0.0.4
Summary: Download videos, documents, etc. from the website
Home-page: https://github.com/ysouyno/yypget
Author: ysouyno
Author-email: ysouyno@163.com
License: MIT
Platform: UNKNOWN
Classifier: Programming Language :: Python :: 3
Classifier: License :: OSI Approved :: MIT License
Classifier: Operating System :: OS Independent
